odoo/addons/stock_request_stage/README.rst
odoo/addons/stock_request_stage/__init__.py
odoo/addons/stock_request_stage/__manifest__.py
odoo/addons/stock_request_stage/i18n/it.po
odoo/addons/stock_request_stage/i18n/stock_request_stage.pot
odoo/addons/stock_request_stage/models/__init__.py
odoo/addons/stock_request_stage/models/stock_request.py
odoo/addons/stock_request_stage/models/stock_request_stage.py
odoo/addons/stock_request_stage/readme/CONFIGURE.md
odoo/addons/stock_request_stage/readme/CONTRIBUTORS.md
odoo/addons/stock_request_stage/readme/DESCRIPTION.md
odoo/addons/stock_request_stage/readme/USAGE.md
odoo/addons/stock_request_stage/security/ir.model.access.csv
odoo/addons/stock_request_stage/static/description/icon.png
odoo/addons/stock_request_stage/static/description/index.html
odoo/addons/stock_request_stage/views/stock_request_menu.xml
odoo/addons/stock_request_stage/views/stock_request_stage_views.xml
odoo/addons/stock_request_stage/views/stock_request_views.xml
odoo_addon_stock_request_stage-17.0.1.0.0.4.dist-info/METADATA
odoo_addon_stock_request_stage-17.0.1.0.0.4.dist-info/WHEEL
odoo_addon_stock_request_stage-17.0.1.0.0.4.dist-info/top_level.txt
odoo_addon_stock_request_stage-17.0.1.0.0.4.dist-info/RECORD
